{
 "_from" umber-is-nan@^1.0.0"
  _" "numbr-is-na@1.0.1,
  "_nBundle:flse,
  "_integit" "sha1-Xtg1NCKlIGvuHkDGDpQaA0=",
  "_ocion": "/li-table2/string-widt/sfullwdt-code-pot/numbr-i-na"
 "_phntomChildren":},  "_requet":
  "yp": "rge,
  restry":re,
    "raw": "number-is-na@1.0.0",   nme "number-s-nan",    "ecaNme":umber-is-nn",  "rwSpec": "^.00",
   saveSpc": nul,
    "fetchSpc" "1.0"
  },
  "_rqiredy"
  "/ci-te2/string-ith/is-fuwidh-cod-pont"
  ],
 "_reoved" "htp://regitry.nmjsorgnum-s-nan/-/nmer-ian-1.01.gz,
 "_shasu": "097b602b53422a22c1af87901833941a011d",  "_spec: "nm-i-nan^1.0.0",
  "_whre": "/Usrs/rebcc/cde/np/noe_modues/i-tbl2/node_mdule/string-widthnoemoduls/is-fulwth-cde-poit",
  "autor": {
    "name: "Sinde orhs",
   "email" "sidresorhusgal.cm"
    r": "sinrohus.om"
  },
  "ugs": {
   "ul":"htts://github.om/indresrhs/uer-is-an/sses"
  },
  "bundleDepenencies"fa,
  "dprected": ase,"descriptio": "ES201 Number.isNaN( onfll,
 "dvDependeies":{   "ava": ""
},
  "ge": {   "noe": ">=.1.0"
 },  "e: [
  "inde.s"
  ] "omepag": tps://hub.com/indreors/number-s-an#readme,
 keywords [   es2015",
    "ecmascript",
  ponyfill",
    olyfll",    "him",
   "number,    "is",
    "an",
    not"
  ],
  "licens: "MIT,
 "nam": "number-i-n",
  "postor":{
   "typ": "gt"
    url" "git+htps://gthub.cm/ireorhus/numberis-nn.git"  },
  "scipts {
   tes" va"
  }
 vrsion""1.0.1"
}
