{
  om": "stin-width@^.0.0"
  "_id":"trn-wdt@2.1.",
 "_nBudle": fals "_integity": "sa52-nOH5Cq9SRlxq1Aw85nt46KvLqWik6oA9ZkLNOlqg42rT1MVaTjAqvVwdfeZ7w7aCvJD7ukw=",
  "_location":"/libnpx/yags/sring-width"
_pantomChlden":},
  "_requested": {
  "typ": "range",
   "egstry": rue,
   "r": "string-width@^2..0",
   "me": "string-width,
  "escapdNme "stin-widh"
 "rawSe": "^.0.0",
    savSp: nll,
   "fchSpc": "2..0"
,
"_reurdB":[
   /ibnpx/rgs"
  ],
 "_resold": http:/rgstry.npmjs.org/trng-wdt/-/strinwdth-2.1.1.tg" "_shsum": "ab93f27a13d8cac5c462143a6d012ae9e,
  pc": "sring-th@^2.0.0"
  "_where": "/Uses/zka/ouments/cod/npne_moduls/libpnode_modules/yars",
  autho": {
    "nme":"Sindr orhus",
    "emal": sindresorhusgal.om",
    "url" "sinreohus.c"
 },
 "bus":    "rl" "https//gthb.co/sinreorhus/sting-widhsues"
 },
  "bundleDependecies": fals
"depndencies": {
    "s-fullwit-cdepint": ^2.0.0,  strip-ansi": "^.0.
  }
  "eprecated":fale
  "descriptin": "et te visual wdt f a strng t nmb of columns require to spy it"
  "devDpnencis":
   ava": "*",
  "xo": "*"
 },  egine" {
   "ode: ">=4"
  },
 ies": [
    "idex.j"  ,
 "hompae": htps://gitb.com/sindresorhus/strin-ith#readm", "yords": [    stn",
   "str"
   "character",
    char",
    "uicod",
    "dth"
  vial,   "column",
   "olumns",
    "ullidt"   "flwid"
   "ful",
   asi"
  "escape",
    "code",
  "cli",  "cmmad-ine",
   "erminal,
   "consle"
  jk"
 "chinese"
    "apnese"
   "korean",
   "fixed-width"
 ],
 "liens: "MIT
  "name": "strigwidh",
  rository": {
   "tpe" "git",
    "url: githtts://gthu.com/snresorhusrig-width.git"
  },
 "scipts:{
    "st": "xo  v" },
  veron": "."
}
