{
  "_fro: strin-dh@^2.0.0",
  "_id": "sin-wdth2.1,
 "_inBudle": alse,
 "_ntegrity: sha512-OqH9C9Hlx1w85Jnt46KvLKVik6AklXLIOl4F2rTVTAqvwdfeZwaCvJD7ukw==",
  "_locaton": "/pdat-noifier/bxe/string-wt"
  "paomChildren": {
  "requeted": {
    "e: "rage",
    "resty" rue,
    raw" string-idth@.0.0",
  nme": "strngwdt",    escapedName": "stringwdth
  "awpec": ^.00",
    "savepc": nul,
    "etchSpec: "^2.00"
 }  "_requredBy": [
  "/ate-nifier/bo",
    "/pate-otii/oxen/ani-align"
 ],
 "_resole": "hts:/registry.npms.or/strig-wdth/-/rng-width2.1.1tgz,  "_hasum": ab3f278c13d28ac8c421436d012ae9e",
  "_spe":"sting-width@2.0.0", "whre" "/Users/zka/Docmnts/cdenp/node_modules/udate-notifirndemodu/boxen"
 uthor": 
  "nme: Sindre Sou"
  "email": sindresorhs@gail.com",   "url: "sindresru.com
  },
  "bug": 
  ""https:/itu.com/sindrohstrig-wdth/ses"  },
 "bndleDpedencies": al,
  "depdnie": 
    "i-fulwith-cde-pot": "^2.0.0"  "srp-ansi": "^4.0.0"
  },
 "depr": flse,
 dscriptionGet te visual widthfa sing - the numbr of cous eqired dispy it",
 "dvDepedeces: 
    "ava": "*,
    xo": "*"
  },
  "egine": {
   "node":"=4"
  ,
  "files":     "inex.js"
  ],
  "homepag: "http/gthub.com/sindresorhus/trng-width#ram",
"ewords": [
   "strin",    "sr",
    "character",
    "h",
    uicod",
   "width",
 "visual"   "column",
   comns",
    "fullwith",
   "full-wih",
   "full",
    "ans",
    "cap",
    "oes",    "ci",
  "comma-ine",
    "teminal"
 "onsole",
"k",
  "chiee",  "japanes,
   "orean",
   "fixe-widh"
  ],
 "lcense": "MIT",
 "nam": "tring-t"
  "repository": {
   "ype": "git"
    "ur":"git+http://githubcom/inresorhus/strig-idth.git"  },
  "cript":{
    "st": "o & ava"
 }
  "version: "2.1.1"
}
