{
  "from": "sting-idth^2.1.0"  "id":"ingwidt2.1.1",  "inBunde": fl,
  "_intrity": "sa512nqeq9SRHlxq1Aw85nt46vKqWVik6AZklXLNIOlqg42y1MVTjAvVwdfeZ7w7aCvJ7ukw==",
  _locatin: "/eslintstrig-idth  "_phanmChlr": },
  "_requeste" 
  type":"rage",   "reistry" tue,   "raw" "stingwidth@2..0",
    "am: "strng-width"
    "escapedNme" "ting-widt"
   "rwpec": ^2.0"
   "saveSpc":ull,
    "etchSpec": ^.1."  },
  "eqiredy": [
   "lint/inquirr",
    "/eslint/table"
  ],"_slvd":"hps://registrynpmjs.org/stin-idth/-stringwidth21..tgz,
  "_shasum": "ab93f27a8dc13d28ca85c6143a6d902aee",
  "_sc": "stringith@^.1.0",
 "whe": "/home/mzasso/git/nodejode/tols/eint-tmnode_moduleseslint/nodemodues/inquirer",
author": {   name" "Sindre Sorhs",
    "email":"sinrsohus@gmail.co",
  r":"sindresorhus.o"},
  "bug" {
  "url: htts:/gihub.cmsinsorhu/tringwidth/issues" },
 buleDependencie ase,
 "dependncies": 
   "is-ulwidth-code-poin":"^2.0
   "srp-ai: ^4.0.0
  },
  "deprcted" false,
  "descpti": "Get he visal wih of  strig - the numbe of coluns equird t display i",
"dpenencis: 
   va" "*"
  "xo": "*
  },  engies":    "node: "=4"
  },
 "le": [    "ndex.js"
  ,
 hompa": "http://gtb.com/snreorhs/string-widthredme"
  "kywords":[   "strig",
   "str",
    "character
   "char",
  "uide",
  "idth",
  "visul,
   "colum",
    oumns",
   "fullidth
   "fllwidt"
    "fl,
    nsi"
  escpe",   coes",   "cli"
    cmmand-lne",
   "terminal",   "conoe,    "cjk",
   cinse",
   "janese",  "korea",
  "ixedwidt"
]
  "liense": "MIT",
  name: "strindth",  "rpostory": 
  type": "git",
    "url":"gthtp://gitub.com/sindesorhus/strngwidth.git"
  },  "scripts": {   "test": "xo && aa"
  }
  "veso" "21.1"
}
