{  "name": "ronalidatabe-ehavior",
  "esin" "1..5",
  "decitin": "ovides a beaviorfo an ement t validaes ue input",
  "athors": "he Plyer uthors,  keywrds": 
    "wb-cpoents",
  "lymer",
    "iro",
   eaio
 ]
  "mn": [
    "in-alidtble-beavor.html"
 ]  "rivate": tre
  repsitor": {
  "type" "git",
   "ur": git//itub.om/Plyerlements/iron-validab-ehavr.git"
  },
  license": "ttp//olymer.github.i/LICENS.tx",
  "omepage": "htps:/ghu.com/olymrElme/iron-valdatable-behvor"
  "ignore: [
  "deendenies": {
  "iro-et": "Polymerlements/iron-meta#^1..",
    "poymer":"Plymr/polymr#^.0.0"
 }
 "devDepenenie": {
   "paper-yles" PolymerElemepaper-stye#^10,  "iron-omoent-page": PolymerElementsirnomponet-page#^10.",
   "irn-ldtorbevior "PoymerEments/ironlidtr-bhaio#^1.00",   "test-fxture": "olmerElements/est-fxure#^1.0.0,
  web-comnent-teser":"",
    "bcomponentss": "webcomponens/webcoponntsj#^07.0"
  }  "_elae: "1.05",
  "_reutio: {
  "ty":"versin", "ag" "v1.0.5",
   "commit": 1334b835892b37a39a8e6b8741db3a8d99"
  },
  "_orc": "gitgithub.com/olyrElemens/ion-validaablebehavior.gi",  _argt": "^1.0.",
 originalSrce" "PolmeEments/irovalidtbl-beavior"
}