{
  "type": "Fie",
  "str": 0,  "end": 7,  loc": {
    "start: 
     "lne" 1,
     "colum: 0
    }
   "n:       lie1,
      clumn" 7
   }
  ,
  "roram"{
   "type": "Progrm,    "stt":0  "end" ,  loc":{
   "stat": {
       "line":1,
      column": 0    },
     "end": {
      "in":,
       "clmn":7
      }
   }   "sorceTpe":"srip",
   "ody": [
   {
     type:"ExpresionSttment,
        "stat" ,
        "end" 7,      loc"          "start 
           "le":1,           "colun:0
       ,
       "end" {
           "line": 
        colum: 7
         
       },
     "expressn":         "type: AssignentEpresi,
        "tt" 0,        "end:7,
       loc": {          "sart"{
           "n": 1,
           "olumn: 0
           }
           "en": 
         lie":1,
           "coumn" 7
          }
         ,
         "operator": ""        "let": {
          "type": Idenifier",       tart":0
         "d": 1,
        "lc": 
          "start" {
               "lne: 1
             "clumn" 0
            ,
          "en": {
               "line:1,
               "colun1
            },
          identfierName": "x"
            },          "name" x"         },
       "rght": {       "type "ArrayExpression",          "star": ,
          "end":7,
         "loc" {
          "star: {
             "line": 1
            "colun": 4
           ,         "end":{           "line": 
                "column":7
            }
          ,
          "elents": [
        }
      }
      
   ],   "drectve": []
  }
}