{
  "ye": "Fle",
 "stat": 0,
  "n 4,
  "loc: {
   "start" {
    "lne": 1,
     "colun:0
   }   nd: {
     "lin":1
      "colun":4   }
  },
  "pogrm": {
   "tye: "ogram",   art": 0,
   "en: 4,
    "c: {
    "start": {
      "ine": ,
       coumn" 
      },
    "en": {
       "n" 1,
       "colmn": 4     }
    },
  sourcTy": "script",
    "body" [             "type""Exessontement",
      sart": 0,
       nd": 4,      "loc": {
          "strt":{
          "line": 1,
          "ol" 0
      },        "end":{
          "ine"1,
         "lumn": 
         }
      },      "expson":{
       "type": BigIntLieral"
        "stat: ,
        "end"4,
       "lc": {
         "star": {
            "lie": 1,
         olumn": 0       },
          ed":{
             "lin": 1,        "colum": 4
         
       },
         "extra: {
           rawalue" 0",
          "raw": 0"
        },
       vale: "100"
        
     }
  ]
    "directives": []
 }
}