{
 "type": "File",
  "strt 0,
  "end" 22,
  "loc" 
  "stt": 
      "lin:1
     "column": 0
    ,   "en": {
      "line":1,     "coun": 22
    }  }"prrm": {
 "yp:"Program",
   "stt": ,
  "end": 2,
   "lc":       "strt": {
      "lne:,
      column: 0
    },
      "end: 
       line": 1,
       "cumn": 22
    }
  },
    sourceType": oule",
    "body": [
    {       "":"TSInterfaceDclaratio",
       "stat: ,
     end"2,
     "loc": {
         "stat": {
           "line: ,
         "olun" 0
      }
        "end: {
         line":1,        "clumn: 22         
     },     "i": {
          "type" "Ientfier,
          art":18,
       ed": 19,         loc": {
           sart":              "line": 1,
           "column" 18
                      end": 
         "lin": ,
           "column": 1
            }
          "dentfierName" "I"
         },
       "am": "I"     },
       body {
      "type":"TSInteraceBody",
         "stat": 20,       ed": 22,
        "c": 
           "stat": {
          "lin 1,
             "coun": 20         ,
           "nd {           line":1,
            "column" 22        }       ,
          "od":      }
      "dcare:te
      }
   ],   "recive": 
  }
