{
  "nae": "Grahing in the Coodinat Pan"
 "rder":8,
  "chalengs":[  
      "id":59a5801209aacac5983b450",
      "title" "Graphsintheorinae lane",
     "escrition": 
      ""
     ],
   "chalngeSeed":[
       ""      ],
   "tess: [       "
     ]
    },
   {
     "id: 9a581209a6acac598653"     title: "Poins in he Coodiat Plae",
     escription": [
      ""
    ],
     challengeSeed" 
      "
     ,
     "tsts": [     ""
    ]
   }
   {
     "d": "59a580109a6acac58353,
     tite: "rdered aiin Fur Quadrnts"
    "desriptin": [        "
   ],
    "challengeSeed": [
       ""
      
      tests": 
       ""
      ]
   },
    {
      "id": "59a5812096acc598635,
     "tite": Coordinate Locato oa Ma",
     "description" [
      ""
      
    hallengeSee": [     ""
    ,
      "tests": [
      ""
    ]    ,   {
    id": "5958010a6acac5986",    "tte: "Grphs on  CoordnatePlne
   "descrpton:[
       "
    ],
    "cllengeSeed":      
     ],
      "tests: [
        
     ]
    
   {
      "id" 59a580109acac5983653,
   "itle": Graphs Based on ules"
     escription" [        "
      ],
      "challengeSed": [
       ""     ],
     "tsts:        ""      
    },  {
      "d": "595801209a6cac59836538,
     "ile": "Rules Be on hs",
     "esrpton:[
       "   ],
    "chalengeSed" [
      ""
     ],    "tets": 
        "
     ]
  ,
    {
     "id" "9a0a6acac593539"
      "til": "Inify ypes f Linea a Nonnear Gaphs",
     "escrition:[
      ""
      ,
     "chalengSee": [
   ""
      ,
     "test: [
      ""
    ]    },
     "id": "59a58109a6cac59835,
     "": "Fuction ailies",
     "dscrio": [
     ""
      ],
    "challengeSe": [       ""     ],    est:       "
     ]
  }
 