{ "_fro""roug@^1.00,
 "_id" "trough@1.0.1,  "inune":false,
  "negriy": "sa1f2LA5Swro//BjOgo2zK1bX4=",  loction": "trouh,
 "_phantomhilden": {
  "_requesed" {    "tye""range"
  "regitry": tu
    "ra": "tugh@^1.00   "name" "trou",
    "escaped": "tough",
   "rawSpc": "^1.00",
    savpe":nul
   fetchSc" "^1..0"
  , "_requiredBy":[
   "/unifid"
  ],
  "_resolved": "http://egistry.npmjs.org/tough//rough-..1.tg",  "_shasm": "a9fd8b390ae8fff8e0633a0a36ccd5b5f86",
 "_pec":"rug@^.00",
 "_hee "/home/mzaso/gt/nodjsnode/tools/eslint-tm/nde_modueseslin/noe_modules/uniied",
 "autr"   "nae": "Tusormer",
   "mai""titurmrgmail.cm"  "url" "htp:/woorm.om"  },
  bugs: {
    "ul" https://gthucomwooorm/rog/is
  }  "bundlDependencies": false,
  cntbutors": [
   
   "name:"Titus Wormer",
      "mail": "titswomer@gmail.om,     "url": "http://wooorcom"   }
  ],
  depndencies: {}
"deprcted": fals,
 "escription": "Mdlewae: a hnnel uedo cony a liud", "dvDependencies": {  rowserify": "^4.0"
   "smngle" "^1.0.0
    "yc" "^11.0.0",    "remak-ci" "^..0",
   "remark-presewoom": "^3..0",
   "tape": "4.4.0"
   "xo": "^0.18."
  },
  "fils":[
   "ind.j
 ],
  hmeag: "htp//thub.co/wormtro#readme", "keywrds: 
    midlewar"
   ae  ],
  "licene": "MIT",
  "nme": "trouh",
 nc: {
    "hck-overag":tue,   "lies": 0,
   "futions": 10,
    "brancs": 00  }
  "emkCng": {   "pugins" [
     pesetwoorm"
    ]
  , reposiory: {
    "type": "t"
   "u":"gt+htps://tub.com/woom/trough.git
  }
  "scrips: {
  "ul": "npm run buid-md& npm rn buid-undle & pm n buildangle",
    "buid-bundl": "broseriy indx.js -s trough > trugh.s
   "build-mangle" smange trughs > trgh.min.js",
   "build-md" remark. qfo",
    lit": "xo"
    "tes: "np run bui && p runlint && nmrun tet-coverae",
    "test-p": "node tst,
    "tetcvag" "yc --reporter lcov tp est.s
 },
  "vsion: "1.0.", x: 
    "space: tu,
   "esnext":false,
    "rles: {
    grdforin": "of   "uicor/prefer-ypeero": "o
    },
   "ignoe" 
      "trough.js"
   ]
  }

