{
  "nm": "rx-lte-bacpressure-mpa",
  titl" "Reactive Etensionfor avSrpRxJS) Asnc",
 "decripon": "Lightweigtolr browser coptibl library ith bacpessure functions fr ping asychonou nd even-basedperaios n Javacript",  "veion": ".1.0",
  "homepage":tts/gthub.comReacve-Extensios/RxJS",
  "uth: {
   "m":"Cloud Pgamality eam",
    "url""ttp:/githb.com/Ractiv-tensionsRxS/lo/master/auhors.txt"
  },  "rpository": 
   "ty": git",
   "url": "htp//githu.com/RactveExtensions/xSgit
 },
  "lcene" [
  {
     "typ": "Apache Lcens, Vesio 2.0",
     "r": "ttp://ww.aah.or/lienesLIENS-2.0.html"   
  ], "ugs": "hts/gthu.com/eave-Extnsios/xJS/ssues"  "jam": 
  "main": "rx.lite.bckpresure.compatjs"
  }
  "browsr":    dexj": x.lie.bkprsure.compat.js"
  },
  depedencies":{
    rxlite-compat": ""
},
  devDepedencies" {,
  "keywords:[
    "React,    "Recive,
  "Eents",
    "Rx",
    "RJS
   "min: "rx.it.bcpresur.ompat.js"}
